ninja_put_patch_file_upload_middleware/middlewares.py
ninja_put_patch_file_upload_middleware-0.1.4.dist-info/LICENSE
ninja_put_patch_file_upload_middleware-0.1.4.dist-info/METADATA
ninja_put_patch_file_upload_middleware-0.1.4.dist-info/WHEEL
ninja_put_patch_file_upload_middleware-0.1.4.dist-info/RECORD
