Metadata-Version: 2.1
Name: ninja-put-patch-file-upload-middleware
Version: 0.1.4
Summary: A middleware that allows user to upload files using PUT / Patch
License: MIT
Keywords: ninja,django-ninja,middlewares,put,patch,file upload
Author: baseplate-admin
Author-email: 61817579+baseplate-admin@users.noreply.github.com
Requires-Python: >=3.10
Classifier: Development Status :: 5 - Production/Stable
Classifier: Framework :: Django
Classifier: Framework :: Django :: 3.2
Classifier: Framework :: Django :: 4.1
Classifier: Framework :: Django :: 4.2
Classifier: Framework :: Django :: 5.0
Classifier: Framework :: Django :: 5.1
Classifier: Intended Audience :: Developers
Classifier: License :: OSI Approved :: MIT License
Classifier: Operating System :: OS Independent
Classifier: Programming Language :: Python
Classifier: Programming Language :: Python :: 3
Classifier: Programming Language :: Python :: 3.10
Classifier: Programming Language :: Python :: 3.11
Classifier: Programming Language :: Python :: 3.12
Classifier: Programming Language :: Python :: 3.13
Classifier: Programming Language :: Python :: 3.9
Classifier: Programming Language :: Python :: Implementation :: PyPy
Classifier: Topic :: Internet :: WWW/HTTP :: WSGI :: Middleware
Requires-Dist: asgiref (>=3.6)
Requires-Dist: django-ninja
Project-URL: Bug Tracker, https://github.com/baseplate-admin/ninja_put_patch_file_upload_middleware/issues
Project-URL: homepage, https://github.com/baseplate-admin/ninja_put_patch_file_upload_middleware
Project-URL: repository, https://github.com/baseplate-admin/ninja_put_patch_file_upload_middleware
